flake8_typing_import_style/__init__.py
flake8_typing_import_style-0.5.0.dist-info/entry_points.txt
flake8_typing_import_style-0.5.0.dist-info/COPYING
flake8_typing_import_style-0.5.0.dist-info/WHEEL
flake8_typing_import_style-0.5.0.dist-info/METADATA
flake8_typing_import_style-0.5.0.dist-info/RECORD
