Metadata-Version: 2.1
Name: flake8-typing-import-style
Version: 0.5.0
Summary: A flake8 plugin to ensure typing module import convention
Home-page: https://github.com/jnoortheen/flake8-import-style
License: ISC
Author: Stefano Palazzo
Author-email: stefano.palazzo@gmail.com
Requires-Python: >=3.6,<4
Classifier: Framework :: Flake8
Classifier: License :: OSI Approved
Classifier: License :: OSI Approved :: ISC License (ISCL)
Classifier: Programming Language :: Python
Classifier: Programming Language :: Python :: 3
Classifier: Programming Language :: Python :: 3.6
Classifier: Programming Language :: Python :: 3.7
Classifier: Programming Language :: Python :: 3.8
Classifier: Programming Language :: Python :: 3.9
Classifier: Topic :: Software Development :: Libraries :: Python Modules
Classifier: Topic :: Software Development :: Quality Assurance
Requires-Dist: flake8 (>=3.8.4,<4.0.0)
Requires-Dist: setuptools
